{
  "family_steps": {
    "step_1": "Δημιουργήστε μια παρουσία της κλάσης \"Editor\" με υποχρεωτική διαδρομή αρχείου ή ροή byte και φορτώστε το αρχείο {{EXT}}",
    "step_2": "Δημιουργήστε και ορίστε την παρουσία κλάσης `EmailEditOptions` για τη μορφή αρχείου {{EXT}}",
    "step_3": "Καλέστε τη μέθοδο `Editor.Edit()` και αποκτήστε έγγραφο {{EXT}} σε μορφή HTML που είναι εύκολα επεξεργάσιμο με οποιοδήποτε πρόγραμμα επεξεργασίας WYSIWYG.",
    "step_4": "Καλέστε τη μέθοδο «Editor.Save()» και αποθηκεύστε το επεξεργασμένο αρχείο {{EXT}} χρησιμοποιώντας την τάξη «EmailSaveOptions»"
  }
}